wrh
